Workbook

Sheet Costing Calculator - Integrated
A1: Cost and Pricing Calculator
B2: Set Desired Margin: | C2: 0.65
B4: TOTAL ENGAGEMENT COSTS AND PRICE
B5: Phase | C5: Cost | D5: Price | F5: Per Head Pricing
B6: DESIGN | C6: =H20 | D6: =J20 | F6: # of Participants/Cohort: | G6: 20
B7: DEVELOPMENT | C7: =H38 | D7: =J38 | F7: Cost per Head - CH1: | G7: =D9/G6 | H7: Reflects all design, development and delivery client costs
B8: DELIVERY | C8: =H106 | D8: =J106 | F8: Cost per Head - CH2: | G8: =D8/G6 | H8: Reflects only delivery client costs
B9: Totals: | C9: =SUM(C6:C8) | D9: =SUM(D6:D8)
B11: ITEM | C11: ITEM COST | D11: NOTE | E11: QUANTITY | F11: COST | G11: PM FEE (12%) | H11: COST W PM | I11: MARGIN | J11: CLIENT PRICE
A12: Design | B12: Learning Design Sprint (Design Document) | C12: 6000 | D12: Flat fee | F12: =IF(ISNUMBER(E12), E12*C12, "") | G12: =IF(OR(ISBLANK(F12), NOT(ISNUMBER(F12))), "", F12 * 0.12) | H12: =IF(OR(ISBLANK(G12), NOT(ISNUMBER(G12))), "", F12+G12) | I12: =$C$2 | J12: =IF(AND(ISNUMBER(H12), I12<1), H12/(1-I12), "") | K12: Changed client price from $10K to 6500
B13: F2F Hackathon - 1 Day | C13: 1500 | D13: Flat fee | F13: =IF(ISNUMBER(E13), E13*C13, "") | G13: =IF(OR(ISBLANK(F13), NOT(ISNUMBER(F13))), "", F13 * 0.12) | H13: =IF(OR(ISBLANK(G13), NOT(ISNUMBER(G13))), "", F13+G13) | I13: =$C$2 | J13: =IF(AND(ISNUMBER(H13), I13<1), H13/(1-I13), "") | K13: Change to Design Lab, and a per day costing (not multiple items)
B14: F2F Hackathon - 2 Day | C14: 3000 | D14: Flat fee | F14: =IF(ISNUMBER(E14), E14*C14, "") | G14: =IF(OR(ISBLANK(F14), NOT(ISNUMBER(F14))), "", F14 * 0.12) | H14: =IF(OR(ISBLANK(G14), NOT(ISNUMBER(G14))), "", F14+G14) | I14: =$C$2 | J14: =IF(AND(ISNUMBER(H14), I14<1), H14/(1-I14), "")
B15: F2F Hackathon - 3 Day | C15: 4500 | D15: Flat fee | F15: =IF(ISNUMBER(E15), E15*C15, "") | G15: =IF(OR(ISBLANK(F15), NOT(ISNUMBER(F15))), "", F15 * 0.12) | H15: =IF(OR(ISBLANK(G15), NOT(ISNUMBER(G15))), "", F15+G15) | I15: =$C$2 | J15: =IF(AND(ISNUMBER(H15), I15<1), H15/(1-I15), "")
B16: F2F Hackathon - 4 Day | C16: 6000 | D16: Flat fee | F16: =IF(ISNUMBER(E16), E16*C16, "") | G16: =IF(OR(ISBLANK(F16), NOT(ISNUMBER(F16))), "", F16 * 0.12) | H16: =IF(OR(ISBLANK(G16), NOT(ISNUMBER(G16))), "", F16+G16) | I16: =$C$2 | J16: =IF(AND(ISNUMBER(H16), I16<1), H16/(1-I16), "")
B17: F2F Hackathon - 5 Day | C17: 7500 | D17: Flat fee | F17: =IF(ISNUMBER(E17), E17*C17, "") | G17: =IF(OR(ISBLANK(F17), NOT(ISNUMBER(F17))), "", F17 * 0.12) | H17: =IF(OR(ISBLANK(G17), NOT(ISNUMBER(G17))), "", F17+G17) | I17: =$C$2 | J17: =IF(AND(ISNUMBER(H17), I17<1), H17/(1-I17), "")
B18: Virtual Hackathon - 4hr | C18: 750 | D18: Flat fee | F18: =IF(ISNUMBER(E18), E18*C18, "") | G18: =IF(OR(ISBLANK(F18), NOT(ISNUMBER(F18))), "", F18 * 0.12) | H18: =IF(OR(ISBLANK(G18), NOT(ISNUMBER(G18))), "", F18+G18) | I18: =$C$2 | J18: =IF(AND(ISNUMBER(H18), I18<1), H18/(1-I18), "")
B19: Virtual Hackathon - 8hr | C19: 1500 | D19: Flat fee | F19: =IF(ISNUMBER(E19), E19*C19, "") | G19: =IF(OR(ISBLANK(F19), NOT(ISNUMBER(F19))), "", F19 * 0.12) | H19: =IF(OR(ISBLANK(G19), NOT(ISNUMBER(G19))), "", F19+G19) | I19: =$C$2 | J19: =IF(AND(ISNUMBER(H19), I19<1), H19/(1-I19), "")
B20: DESIGN TOTAL: | F20: =SUM(F12:F19) | G20: =SUM(G12:G19) | H20: =SUM(H12:H19) | J20: =SUM(J12:J19)
B22: ITEM | C22: ITEM COST | D22: NOTE | E22: QUANTITY | F22: COST | G22: PM FEE (12%) | H22: COST W PM | I22: MARGIN | J22: CLIENT PRICE | K22: Simplify - development of up to 2 hrs of virtual content, F2F content, etc. Combine similar things.
A23: Development | B23: Pre-Program Capstone | C23: =M23 | D23: Flat fee (design only) | F23: =IF(ISNUMBER(E23), E23*C23, "") | G23: =IF(OR(ISBLANK(F23), NOT(ISNUMBER(F23))), "", F23 * 0.12) | H23: =IF(OR(ISBLANK(G23), NOT(ISNUMBER(G23))), "", F23+G23) | I23: =$C$2 | J23: =IF(AND(ISNUMBER(H23), I23<1), H23/(1-I23), "") | K23: Eliminate | L23: 6500 | M23: =L23*0.3
B24: Post-Program Capstone | C24: 1950 | D24: Flat fee (design only) | F24: =IF(ISNUMBER(E24), E24*C24, "") | G24: =IF(OR(ISBLANK(F24), NOT(ISNUMBER(F24))), "", F24 * 0.12) | H24: =IF(OR(ISBLANK(G24), NOT(ISNUMBER(G24))), "", F24+G24) | I24: =$C$2 | J24: =IF(AND(ISNUMBER(H24), I24<1), H24/(1-I24), "") | K24: Change to Capstone Session. Not part of a Business impact project, just a program capstone.
B25: Immersive Learning Offsite (1-day F2F) | C25: 5500 | D25: Per day (design only) | F25: =IF(ISNUMBER(E25), E25*C25, "") | G25: =IF(OR(ISBLANK(F25), NOT(ISNUMBER(F25))), "", F25 * 0.12) | H25: =IF(OR(ISBLANK(G25), NOT(ISNUMBER(G25))), "", F25+G25) | I25: =$C$2 | J25: =IF(AND(ISNUMBER(H25), I25<1), H25/(1-I25), "") | K25: Needs to revise down. Call out Per Day.. | L25: 6500 | M25: =L25*0.3
B26: 2-hour Tailored Learning Experience/Session (Learning Circle, Action Learning, AppEx) | C26: =M26 | D26: Flat fee (design only) | F26: =IF(ISNUMBER(E26), E26*C26, "") | G26: =IF(OR(ISBLANK(F26), NOT(ISNUMBER(F26))), "", F26 * 0.12) | H26: =IF(OR(ISBLANK(G26), NOT(ISNUMBER(G26))), "", F26+G26) | I26: =$C$2 | J26: =IF(AND(ISNUMBER(H26), I26<1), H26/(1-I26), "") | L26: 6500 | M26: =L26*0.3
B27: 2-hour Customized Learning Experience/Session (Learning Circle, Action Learning, AppEx) | C27: 2300 | D27: Flat fee (design only) | F27: =IF(ISNUMBER(E27), E27*C27, "") | G27: =IF(OR(ISBLANK(F27), NOT(ISNUMBER(F27))), "", F27 * 0.12) | H27: =IF(OR(ISBLANK(G27), NOT(ISNUMBER(G27))), "", F27+G27) | I27: =$C$2 | J27: =IF(AND(ISNUMBER(H27), I27<1), H27/(1-I27), "")
B28: Insight Cafe | C28: 900 | D28: Flat fee (design only) | F28: =IF(ISNUMBER(E28), E28*C28, "") | G28: =IF(OR(ISBLANK(F28), NOT(ISNUMBER(F28))), "", F28 * 0.12) | H28: =IF(OR(ISBLANK(G28), NOT(ISNUMBER(G28))), "", F28+G28) | I28: =$C$2 | J28: =IF(AND(ISNUMBER(H28), I28<1), H28/(1-I28), "")
B29: Behavior Activation Toolkit | C29: 3750 | D29: Flat fee | F29: =IF(ISNUMBER(E29), E29*C29, "") | G29: =IF(OR(ISBLANK(F29), NOT(ISNUMBER(F29))), "", F29 * 0.12) | H29: =IF(OR(ISBLANK(G29), NOT(ISNUMBER(G29))), "", F29+G29) | I29: =$C$2 | J29: =IF(AND(ISNUMBER(H29), I29<1), H29/(1-I29), "")
B30: Values/Principles Immersive Learning Offsite (F2F) | C30: 5500 | D30: Per day (design only) | F30: =IF(ISNUMBER(E30), E30*C30, "") | G30: =IF(OR(ISBLANK(F30), NOT(ISNUMBER(F30))), "", F30 * 0.12) | H30: =IF(OR(ISBLANK(G30), NOT(ISNUMBER(G30))), "", F30+G30) | I30: =$C$2 | J30: =IF(AND(ISNUMBER(H30), I30<1), H30/(1-I30), "")
B31: Action Learning Brief | C31: 990 | D31: Per unit | F31: =IF(ISNUMBER(E31), E31*C31, "") | G31: =IF(OR(ISBLANK(F31), NOT(ISNUMBER(F31))), "", F31 * 0.12) | H31: =IF(OR(ISBLANK(G31), NOT(ISNUMBER(G31))), "", F31+G31) | I31: =$C$2 | J31: =IF(AND(ISNUMBER(H31), I31<1), H31/(1-I31), "") | K31: What is this? Facilitator debrief?
B32: Dialogue Toolkit | C32: 3750 | D32: Flat fee | F32: =IF(ISNUMBER(E32), E32*C32, "") | G32: =IF(OR(ISBLANK(F32), NOT(ISNUMBER(F32))), "", F32 * 0.12) | H32: =IF(OR(ISBLANK(G32), NOT(ISNUMBER(G32))), "", F32+G32) | I32: =$C$2 | J32: =IF(AND(ISNUMBER(H32), I32<1), H32/(1-I32), "") | K32: convert to a less expensive discussion guide. No deck/content.
B33: Peer Coaching | C33: 450 | D33: Per unit | F33: =IF(ISNUMBER(E33), E33*C33, "") | G33: =IF(OR(ISBLANK(F33), NOT(ISNUMBER(F33))), "", F33 * 0.12) | H33: =IF(OR(ISBLANK(G33), NOT(ISNUMBER(G33))), "", F33+G33) | I33: =$C$2 | J33: =IF(AND(ISNUMBER(H33), I33<1), H33/(1-I33), "")
B34: Principles/Values Workshop (Tailored) | C34: 2300 | D34: Flat fee (design only) | F34: =IF(ISNUMBER(E34), E34*C34, "") | G34: =IF(OR(ISBLANK(F34), NOT(ISNUMBER(F34))), "", F34 * 0.12) | H34: =IF(OR(ISBLANK(G34), NOT(ISNUMBER(G34))), "", F34+G34) | I34: =$C$2 | J34: =IF(AND(ISNUMBER(H34), I34<1), H34/(1-I34), "")
B35: SkillStream (1 path) | C35: 10500 | D35: Flat fee | F35: =IF(ISNUMBER(E35), E35*C35, "") | G35: =IF(OR(ISBLANK(F35), NOT(ISNUMBER(F35))), "", F35 * 0.12) | H35: =IF(OR(ISBLANK(G35), NOT(ISNUMBER(G35))), "", F35+G35) | I35: =$C$2 | J35: =IF(AND(ISNUMBER(H35), I35<1), H35/(1-I35), "")
B36: SkillStream (2 path) | C36: 20100 | D36: Flat fee | F36: =IF(ISNUMBER(E36), E36*C36, "") | G36: =IF(OR(ISBLANK(F36), NOT(ISNUMBER(F36))), "", F36 * 0.12) | H36: =IF(OR(ISBLANK(G36), NOT(ISNUMBER(G36))), "", F36+G36) | I36: =$C$2 | J36: =IF(AND(ISNUMBER(H36), I36<1), H36/(1-I36), "")
B37: Learning Lab | C37: 7500 | D37: Flat fee | F37: =IF(ISNUMBER(E37), E37*C37, "") | G37: =IF(OR(ISBLANK(F37), NOT(ISNUMBER(F37))), "", F37 * 0.12) | H37: =IF(OR(ISBLANK(G37), NOT(ISNUMBER(G37))), "", F37+G37) | I37: =$C$2 | J37: =IF(AND(ISNUMBER(H37), I37<1), H37/(1-I37), "")
B38: DEVELOPMENT TOTAL: | F38: =SUM(F23:F37) | G38: =SUM(G23:G37) | H38: =SUM(H23:H37) | J38: =SUM(J23:J37)
G39: =IF(OR(ISBLANK(F39), NOT(ISNUMBER(F39))), "", F39 * 0.12) | H39: =IF(OR(ISBLANK(G39), NOT(ISNUMBER(G39))), "", F39+G39)
B40: ITEM | C40: ITEM COST | D40: NOTE | E40: QUANTITY | F40: COST | G40: PM FEE (12%) | H40: COST W PM | I40: MARGIN | J40: CLIENT PRICE
A41: Delivery | B41: ASSESSMENT
B42: CMI Assessment | C42: 100 | D42: Per person | F42: =IF(ISNUMBER(E42), E42*C42, "") | G42: =IF(OR(ISBLANK(F42), NOT(ISNUMBER(F42))), "", F42 * 0.12) | H42: =IF(OR(ISBLANK(G42), NOT(ISNUMBER(G42))), "", F42+G42) | I42: 0 | J42: =IF(AND(ISNUMBER(H42), I42<1), H42/(1-I42), "")
B43: CMI 360 Report | C43: 250 | D43: Per person | F43: =IF(ISNUMBER(E43), E43*C43, "") | G43: =IF(OR(ISBLANK(F43), NOT(ISNUMBER(F43))), "", F43 * 0.12) | H43: =IF(OR(ISBLANK(G43), NOT(ISNUMBER(G43))), "", F43+G43) | I43: 0 | J43: =IF(AND(ISNUMBER(H43), I43<1), H43/(1-I43), "")
B44: CMI Group Report | C44: 150 | D44: Per cohort | F44: =IF(ISNUMBER(E44), E44*C44, "") | G44: =IF(OR(ISBLANK(F44), NOT(ISNUMBER(F44))), "", F44 * 0.12) | H44: =IF(OR(ISBLANK(G44), NOT(ISNUMBER(G44))), "", F44+G44) | I44: 0 | J44: =IF(AND(ISNUMBER(H44), I44<1), H44/(1-I44), "")
B45: LD12 Assessment | C45: 150 | D45: Per person | F45: =IF(ISNUMBER(E45), E45*C45, "") | G45: =IF(OR(ISBLANK(F45), NOT(ISNUMBER(F45))), "", F45 * 0.12) | H45: =IF(OR(ISBLANK(G45), NOT(ISNUMBER(G45))), "", F45+G45) | I45: 0 | J45: =IF(AND(ISNUMBER(H45), I45<1), H45/(1-I45), "")
B46: LD12 360 Assessment | C46: 350 | D46: Per person | F46: =IF(ISNUMBER(E46), E46*C46, "") | G46: =IF(OR(ISBLANK(F46), NOT(ISNUMBER(F46))), "", F46 * 0.12) | H46: =IF(OR(ISBLANK(G46), NOT(ISNUMBER(G46))), "", F46+G46) | I46: 0 | J46: =IF(AND(ISNUMBER(H46), I46<1), H46/(1-I46), "")
B47: Core Values Navigator | C47: 150 | D47: Per person | F47: =IF(ISNUMBER(E47), E47*C47, "") | G47: =IF(OR(ISBLANK(F47), NOT(ISNUMBER(F47))), "", F47 * 0.12) | H47: =IF(OR(ISBLANK(G47), NOT(ISNUMBER(G47))), "", F47+G47) | I47: 0 | J47: =IF(AND(ISNUMBER(H47), I47<1), H47/(1-I47), "")
B48: Hogan Insights Series | C48: 300 | D48: Per person | F48: =IF(ISNUMBER(E48), E48*C48, "") | G48: =IF(OR(ISBLANK(F48), NOT(ISNUMBER(F48))), "", F48 * 0.12) | H48: =IF(OR(ISBLANK(G48), NOT(ISNUMBER(G48))), "", F48+G48) | I48: 0 | J48: =IF(AND(ISNUMBER(H48), I48<1), H48/(1-I48), "")
B49: Leadership Genome | C49: 1500 | D49: Per unit | F49: =IF(ISNUMBER(E49), E49*C49, "") | G49: =IF(OR(ISBLANK(F49), NOT(ISNUMBER(F49))), "", F49 * 0.12) | H49: =IF(OR(ISBLANK(G49), NOT(ISNUMBER(G49))), "", F49+G49) | I49: =$C$2 | J49: =IF(AND(ISNUMBER(H49), I49<1), H49/(1-I49), "")
B50: Leadership Blueprint Package | C50: 4500 | D50: Per unit | F50: =IF(ISNUMBER(E50), E50*C50, "") | G50: =IF(OR(ISBLANK(F50), NOT(ISNUMBER(F50))), "", F50 * 0.12) | H50: =IF(OR(ISBLANK(G50), NOT(ISNUMBER(G50))), "", F50+G50) | I50: =$C$2 | J50: =IF(AND(ISNUMBER(H50), I50<1), H50/(1-I50), "")
B51: Leadership Insights Package | C51: 1534.05 | D51: Per person | F51: =IF(ISNUMBER(E51), E51*C51, "") | G51: =IF(OR(ISBLANK(F51), NOT(ISNUMBER(F51))), "", F51 * 0.12) | H51: =IF(OR(ISBLANK(G51), NOT(ISNUMBER(G51))), "", F51+G51) | I51: =$C$2 | J51: =IF(AND(ISNUMBER(H51), I51<1), H51/(1-I51), "")
B52: Leadership Pipeline Package | C52: 6136.2 | D52: Per role | F52: =IF(ISNUMBER(E52), E52*C52, "") | G52: =IF(OR(ISBLANK(F52), NOT(ISNUMBER(F52))), "", F52 * 0.12) | H52: =IF(OR(ISBLANK(G52), NOT(ISNUMBER(G52))), "", F52+G52) | I52: =$C$2 | J52: =IF(AND(ISNUMBER(H52), I52<1), H52/(1-I52), "")
B53: TES Survey (Standard) | C53: 500 | D53: Per team | F53: =IF(ISNUMBER(E53), E53*C53, "") | G53: =IF(OR(ISBLANK(F53), NOT(ISNUMBER(F53))), "", F53 * 0.12) | H53: =IF(OR(ISBLANK(G53), NOT(ISNUMBER(G53))), "", F53+G53) | I53: 0 | J53: =IF(AND(ISNUMBER(H53), I53<1), H53/(1-I53), "")
B54: TES Survey (Bulk, 50-99) | C54: 475 | D54: Per team | F54: =IF(ISNUMBER(E54), E54*C54, "") | G54: =IF(OR(ISBLANK(F54), NOT(ISNUMBER(F54))), "", F54 * 0.12) | H54: =IF(OR(ISBLANK(G54), NOT(ISNUMBER(G54))), "", F54+G54) | I54: 0 | J54: =IF(AND(ISNUMBER(H54), I54<1), H54/(1-I54), "")
B55: TES Survey (Bulk, 100-199) | C55: 470 | D55: Per team | F55: =IF(ISNUMBER(E55), E55*C55, "") | G55: =IF(OR(ISBLANK(F55), NOT(ISNUMBER(F55))), "", F55 * 0.12) | H55: =IF(OR(ISBLANK(G55), NOT(ISNUMBER(G55))), "", F55+G55) | I55: 0 | J55: =IF(AND(ISNUMBER(H55), I55<1), H55/(1-I55), "")
B56: TES Survey (Bulk, 200+) | C56: 460 | D56: Per team | F56: =IF(ISNUMBER(E56), E56*C56, "") | G56: =IF(OR(ISBLANK(F56), NOT(ISNUMBER(F56))), "", F56 * 0.12) | H56: =IF(OR(ISBLANK(G56), NOT(ISNUMBER(G56))), "", F56+G56) | I56: 0 | J56: =IF(AND(ISNUMBER(H56), I56<1), F56+ (G56/(1-I56)), "")
B57: Stakeholder Interview (30 min) | C57: 195 | D57: Per session | F57: =IF(ISNUMBER(E57), E57*C57, "") | G57: =IF(OR(ISBLANK(F57), NOT(ISNUMBER(F57))), "", F57 * 0.12) | H57: =IF(OR(ISBLANK(G57), NOT(ISNUMBER(G57))), "", F57+G57) | I57: =$C$2 | J57: =IF(AND(ISNUMBER(H57), I57<1), H57/(1-I57), "")
B59: Assessment Total: | F59: =SUM(F42:F58) | G59: =SUM(G42:G58) | H59: =SUM(H42:H58) | J59: =SUM(J42:J58)
B60: LD FACILITATION | C60: ITEM COST | D60: NOTE | E60: QUANTITY | F60: COST | G60: PM FEE (12%) | H60: COST W PM | I60: MARGIN | J60: CLIENT PRICE
B61: Virtual Facilitation (NA) - Up to 2hr | C61: 1200 | D61: Per session | F61: =IF(ISNUMBER(E61), E61*C61, "") | G61: =IF(OR(ISBLANK(F61), NOT(ISNUMBER(F61))), "", F61 * 0.12) | H61: =IF(OR(ISBLANK(G61), NOT(ISNUMBER(G61))), "", F61+G61) | I61: =$C$2 | J61: =IF(AND(ISNUMBER(H61), I61<1), H61/(1-I61), "") | L61: 3750 | M61: =L61*0.3
B62: Virtual Facilitation (NA) - 2.5 to 4hr | C62: 2400 | D62: Per session | F62: =IF(ISNUMBER(E62), E62*C62, "") | G62: =IF(OR(ISBLANK(F62), NOT(ISNUMBER(F62))), "", F62 * 0.12) | H62: =IF(OR(ISBLANK(G62), NOT(ISNUMBER(G62))), "", F62+G62) | I62: =$C$2 | J62: =IF(AND(ISNUMBER(H62), I62<1), H62/(1-I62), "") | L62: 4500 | M62: =L62*0.3
B63: Virtual Facilitation (EM) - Up to 2hr | C63: 900 | D63: Per session | F63: =IF(ISNUMBER(E63), E63*C63, "") | G63: =IF(OR(ISBLANK(F63), NOT(ISNUMBER(F63))), "", F63 * 0.12) | H63: =IF(OR(ISBLANK(G63), NOT(ISNUMBER(G63))), "", F63+G63) | I63: =$C$2 | J63: =IF(AND(ISNUMBER(H63), I63<1), H63/(1-I63), "")
B64: Virtual Facilitation (EM) - 2.5 to 4hr | C64: 1800 | D64: Per session | F64: =IF(ISNUMBER(E64), E64*C64, "") | G64: =IF(OR(ISBLANK(F64), NOT(ISNUMBER(F64))), "", F64 * 0.12) | H64: =IF(OR(ISBLANK(G64), NOT(ISNUMBER(G64))), "", F64+G64) | I64: =$C$2 | J64: =IF(AND(ISNUMBER(H64), I64<1), H64/(1-I64), "")
B65: F2F Facilitation Tier 1 (NA) - 1/2 day | C65: 2400 | D65: Per session | F65: =IF(ISNUMBER(E65), E65*C65, "") | G65: =IF(OR(ISBLANK(F65), NOT(ISNUMBER(F65))), "", F65 * 0.12) | H65: =IF(OR(ISBLANK(G65), NOT(ISNUMBER(G65))), "", F65+G65) | I65: =$C$2 | J65: =IF(AND(ISNUMBER(H65), I65<1), H65/(1-I65), "") | L65: 8250 | M65: =L65*0.3
B66: F2F Facilitation Tier 2 (NA) - 1/2 day | C66: 1800 | D66: Per session | F66: =IF(ISNUMBER(E66), E66*C66, "") | G66: =IF(OR(ISBLANK(F66), NOT(ISNUMBER(F66))), "", F66 * 0.12) | H66: =IF(OR(ISBLANK(G66), NOT(ISNUMBER(G66))), "", F66+G66) | I66: =$C$2 | J66: =IF(AND(ISNUMBER(H66), I66<1), H66/(1-I66), "")
B67: F2F Facilitation Tier 1 (NA) - Full day | C67: 4000 | D67: Per session | F67: =IF(ISNUMBER(E67), E67*C67, "") | G67: =IF(OR(ISBLANK(F67), NOT(ISNUMBER(F67))), "", F67 * 0.12) | H67: =IF(OR(ISBLANK(G67), NOT(ISNUMBER(G67))), "", F67+G67) | I67: =$C$2 | J67: =IF(AND(ISNUMBER(H67), I67<1), H67/(1-I67), "")
B68: F2F Facilitation Tier 2 (NA) - Full day | C68: 3000 | D68: Per session | F68: =IF(ISNUMBER(E68), E68*C68, "") | G68: =IF(OR(ISBLANK(F68), NOT(ISNUMBER(F68))), "", F68 * 0.12) | H68: =IF(OR(ISBLANK(G68), NOT(ISNUMBER(G68))), "", F68+G68) | I68: =$C$2 | J68: =IF(AND(ISNUMBER(H68), I68<1), H68/(1-I68), "")
B69: F2F Facilitation Tier 1 (EM) - 1/2 day | C69: 1800 | D69: Per session | F69: =IF(ISNUMBER(E69), E69*C69, "") | G69: =IF(OR(ISBLANK(F69), NOT(ISNUMBER(F69))), "", F69 * 0.12) | H69: =IF(OR(ISBLANK(G69), NOT(ISNUMBER(G69))), "", F69+G69) | I69: =$C$2 | J69: =IF(AND(ISNUMBER(H69), I69<1), H69/(1-I69), "")
B70: F2F Facilitation Tier 2 (EM) - 1/2 day | C70: 1200 | D70: Per session | F70: =IF(ISNUMBER(E70), E70*C70, "") | G70: =IF(OR(ISBLANK(F70), NOT(ISNUMBER(F70))), "", F70 * 0.12) | H70: =IF(OR(ISBLANK(G70), NOT(ISNUMBER(G70))), "", F70+G70) | I70: =$C$2 | J70: =IF(AND(ISNUMBER(H70), I70<1), H70/(1-I70), "")
B71: F2F Facilitation Tier 1 (EM) - Full day | C71: 3000 | D71: Per session | F71: =IF(ISNUMBER(E71), E71*C71, "") | G71: =IF(OR(ISBLANK(F71), NOT(ISNUMBER(F71))), "", F71 * 0.12) | H71: =IF(OR(ISBLANK(G71), NOT(ISNUMBER(G71))), "", F71+G71) | I71: =$C$2 | J71: =IF(AND(ISNUMBER(H71), I71<1), H71/(1-I71), "")
B72: F2F Facilitation Tier 2 (EM) - Full day | C72: 2000 | D72: Per session | F72: =IF(ISNUMBER(E72), E72*C72, "") | G72: =IF(OR(ISBLANK(F72), NOT(ISNUMBER(F72))), "", F72 * 0.12) | H72: =IF(OR(ISBLANK(G72), NOT(ISNUMBER(G72))), "", F72+G72) | I72: =$C$2 | J72: =IF(AND(ISNUMBER(H72), I72<1), H72/(1-I72), "")
B73: Overnight Travel Stipend - up to 4 timzones | C73: 500 | D73: Per trip | F73: =IF(ISNUMBER(E73), E73*C73, "") | G73: =IF(OR(ISBLANK(F73), NOT(ISNUMBER(F73))), "", 0) | H73: =IF(OR(ISBLANK(G73), NOT(ISNUMBER(G73))), "", F73+G73) | I73: 0 | J73: =IF(AND(ISNUMBER(H73), I73<1), H73/(1-I73), "") | K73: Project mgmt fees do not apply; no margin applied
B74: Overnight Travel Stipend - 4 or more timezones | C74: 1000 | D74: Per trip | F74: =IF(ISNUMBER(E74), E74*C74, "") | G74: =IF(OR(ISBLANK(F74), NOT(ISNUMBER(F74))), "", 0) | H74: =IF(OR(ISBLANK(G74), NOT(ISNUMBER(G74))), "", F74+G74) | I74: 0 | J74: =IF(AND(ISNUMBER(H74), I74<1), H74/(1-I74), "") | K74: Project mgmt fees do not apply,; no margin applied
B75: Group Coaching (new pricing) | C75: 1500 | D75: Per session | F75: =IF(ISNUMBER(E75), E75*C75, "") | G75: =IF(OR(ISBLANK(F75), NOT(ISNUMBER(F75))), "", F75 * 0.12) | H75: =IF(OR(ISBLANK(G75), NOT(ISNUMBER(G75))), "", F75+G75) | I75: =$C$2 | J75: =IF(AND(ISNUMBER(H75), I75<1), H75/(1-I75), "") | K75: Changed client price to $5000 | L75: 3750 | M75: =L75*0.3
B76: Assessment Group Debrief (new pricing) | C76: 1200 | D76: Per session | F76: =IF(ISNUMBER(E76), E76*C76, "") | G76: =IF(OR(ISBLANK(F76), NOT(ISNUMBER(F76))), "", F76 * 0.12) | H76: =IF(OR(ISBLANK(G76), NOT(ISNUMBER(G76))), "", F76+G76) | I76: =$C$2 | J76: =IF(AND(ISNUMBER(H76), I76<1), H76/(1-I76), "")
B77: LICENSING
C78: PRICE/MODULE | D78: # OF MODULES | E78: # OF LEARNERS
B79: Licensing | C79: 50 | D79: 6 | F79: =C79*D79*E79 | G79: 0 | H79: =IF(OR(ISBLANK(G79), NOT(ISNUMBER(G79))), "", F79+G79) | I79: 0 | J79: =IF(AND(ISNUMBER(H79), I79<1), H79/(1-I79), "")
B80: LD FACILITATION AND LICENSING TOTAL: | F80: =SUM(F61:F79) | G80: =SUM(G61:G79) | H80: =SUM(H61:H79) | J80: =SUM(J61:J79)
B81: TEAM EFFECTIVENESS
B82: TE Perspectives - half day (1 coach) | C82: 5887.5 | D82: Per team | F82: =IF(ISNUMBER(E82), E82*C82, "") | G82: =IF(OR(ISBLANK(F82), NOT(ISNUMBER(F82))), "", F82 * 0.12) | H82: =IF(OR(ISBLANK(G82), NOT(ISNUMBER(G82))), "", F82+G82) | I82: =$C$2 | J82: =IF(AND(ISNUMBER(H82), I82<1), H82/(1-I82), "")
B83: TE Perspectives - full day (1 coach) | C83: 7312.5 | D83: Per team | F83: =IF(ISNUMBER(E83), E83*C83, "") | G83: =IF(OR(ISBLANK(F83), NOT(ISNUMBER(F83))), "", F83 * 0.12) | H83: =IF(OR(ISBLANK(G83), NOT(ISNUMBER(G83))), "", F83+G83) | I83: =$C$2 | J83: =IF(AND(ISNUMBER(H83), I83<1), H83/(1-I83), "")
B84: TE Perspectives - half day (2 coaches) | C84: 9637.5 | D84: Per team | F84: =IF(ISNUMBER(E84), E84*C84, "") | G84: =IF(OR(ISBLANK(F84), NOT(ISNUMBER(F84))), "", F84 * 0.12) | H84: =IF(OR(ISBLANK(G84), NOT(ISNUMBER(G84))), "", F84+G84) | I84: =$C$2 | J84: =IF(AND(ISNUMBER(H84), I84<1), H84/(1-I84), "")
B85: TE Perspectives - full day (2 coaches) | C85: 12337.5 | D85: Per team | F85: =IF(ISNUMBER(E85), E85*C85, "") | G85: =IF(OR(ISBLANK(F85), NOT(ISNUMBER(F85))), "", F85 * 0.12) | H85: =IF(OR(ISBLANK(G85), NOT(ISNUMBER(G85))), "", F85+G85) | I85: =$C$2 | J85: =IF(AND(ISNUMBER(H85), I85<1), H85/(1-I85), "")
B86: TE Roadmap (1 coach) | C86: 15825 | D86: Per team | F86: =IF(ISNUMBER(E86), E86*C86, "") | G86: =IF(OR(ISBLANK(F86), NOT(ISNUMBER(F86))), "", F86 * 0.12) | H86: =IF(OR(ISBLANK(G86), NOT(ISNUMBER(G86))), "", F86+G86) | I86: =$C$2 | J86: =IF(AND(ISNUMBER(H86), I86<1), H86/(1-I86), "")
B87: TE Roadmap (2 coaches) | C87: 29475 | D87: Per team | F87: =IF(ISNUMBER(E87), E87*C87, "") | G87: =IF(OR(ISBLANK(F87), NOT(ISNUMBER(F87))), "", F87 * 0.12) | H87: =IF(OR(ISBLANK(G87), NOT(ISNUMBER(G87))), "", F87+G87) | I87: =$C$2 | J87: =IF(AND(ISNUMBER(H87), I87<1), H87/(1-I87), "")
B88: TE Ignite (1 coach) | C88: 21930 | D88: Per team | F88: =IF(ISNUMBER(E88), E88*C88, "") | G88: =IF(OR(ISBLANK(F88), NOT(ISNUMBER(F88))), "", F88 * 0.12) | H88: =IF(OR(ISBLANK(G88), NOT(ISNUMBER(G88))), "", F88+G88) | I88: =$C$2 | J88: =IF(AND(ISNUMBER(H88), I88<1), H88/(1-I88), "")
B89: TE Ignite (2 coaches) | C89: 39705 | D89: Per team | F89: =IF(ISNUMBER(E89), E89*C89, "") | G89: =IF(OR(ISBLANK(F89), NOT(ISNUMBER(F89))), "", F89 * 0.12) | H89: =IF(OR(ISBLANK(G89), NOT(ISNUMBER(G89))), "", F89+G89) | I89: =$C$2 | J89: =IF(AND(ISNUMBER(H89), I89<1), H89/(1-I89), "")
B90: Additional Team Coaching (1/2 day, 1 coach) | C90: 2400 | D90: Flat fee | F90: =IF(ISNUMBER(E90), E90*C90, "") | G90: =IF(OR(ISBLANK(F90), NOT(ISNUMBER(F90))), "", F90 * 0.12) | H90: =IF(OR(ISBLANK(G90), NOT(ISNUMBER(G90))), "", F90+G90) | I90: =$C$2 | J90: =IF(AND(ISNUMBER(H90), I90<1), H90/(1-I90), "") | K90: Team Insight Session*
B91: Additional Team Coaching (Full day, 1 coach) | C91: 4000 | D91: Flat fee | F91: =IF(ISNUMBER(E91), E91*C91, "") | G91: =IF(OR(ISBLANK(F91), NOT(ISNUMBER(F91))), "", F91 * 0.12) | H91: =IF(OR(ISBLANK(G91), NOT(ISNUMBER(G91))), "", F91+G91) | I91: =$C$2 | J91: =IF(AND(ISNUMBER(H91), I91<1), H91/(1-I91), "") | K91: Team Insight Session*
B92: Additional Team Coaching (2 hrs) | C92: 2400 | D92: Flat fee | F92: =IF(ISNUMBER(E92), E92*C92, "") | G92: =IF(OR(ISBLANK(F92), NOT(ISNUMBER(F92))), "", F92 * 0.12) | H92: =IF(OR(ISBLANK(G92), NOT(ISNUMBER(G92))), "", F92+G92) | I92: =$C$2 | J92: =IF(AND(ISNUMBER(H92), I92<1), H92/(1-I92), "")
B93: Additional Team Leader Meeting | C93: 2400 | D93: Flat fee | F93: =IF(ISNUMBER(E93), E93*C93, "") | G93: =IF(OR(ISBLANK(F93), NOT(ISNUMBER(F93))), "", F93 * 0.12) | H93: =IF(OR(ISBLANK(G93), NOT(ISNUMBER(G93))), "", F93+G93) | I93: =$C$2 | J93: =IF(AND(ISNUMBER(H93), I93<1), H93/(1-I93), "")
B94: Individual Assessment Debrief (60 min) | C94: 390 | D94: Flat fee | F94: =IF(ISNUMBER(E94), E94*C94, "") | G94: =IF(OR(ISBLANK(F94), NOT(ISNUMBER(F94))), "", F94 * 0.12) | H94: =IF(OR(ISBLANK(G94), NOT(ISNUMBER(G94))), "", F94+G94) | I94: =$C$2 | J94: =IF(AND(ISNUMBER(H94), I94<1), H94/(1-I94), "")
B95: TE CZ Fee | C95: 70 | D95: Per person | F95: =IF(ISNUMBER(E95), E95*C95, "") | G95: =IF(OR(ISBLANK(F95), NOT(ISNUMBER(F95))), "", F95 * 0.12) | H95: =IF(OR(ISBLANK(G95), NOT(ISNUMBER(G95))), "", F95+G95) | I95: 0 | J95: =IF(AND(ISNUMBER(H95), I95<1), H95/(1-I95), "")
B96: TEAM EFFECTIVENESS TOTAL: | F96: =SUM(F82:F89) | G96: =SUM(G82:G89) | H96: =SUM(H82:H89) | J96: =SUM(J82:J89)
B97: EXECUTIVE COACHING
B98: ROADMAP | C98: ='Coaching Calculator'!B5 | D98: Per person | E98: ='Coaching Calculator'!D5 | F98: ='Coaching Calculator'!E5 | G98: ='Coaching Calculator'!F5 | H98: ='Coaching Calculator'!G5 | I98: ='Coaching Calculator'!H5 | J98: ='Coaching Calculator'!I5
B99: IGNITE | C99: ='Coaching Calculator'!B6 | D99: Per person | E99: ='Coaching Calculator'!D6 | F99: ='Coaching Calculator'!E6 | G99: ='Coaching Calculator'!F6 | H99: ='Coaching Calculator'!G6 | I99: ='Coaching Calculator'!H6 | J99: ='Coaching Calculator'!I6
B100: ASCENT | C100: ='Coaching Calculator'!B7 | D100: Per person | E100: ='Coaching Calculator'!D7 | F100: ='Coaching Calculator'!E7 | G100: ='Coaching Calculator'!F7 | H100: ='Coaching Calculator'!G7 | I100: ='Coaching Calculator'!H7 | J100: ='Coaching Calculator'!I7
B101: SPARK 1 | C101: ='Coaching Calculator'!B8 | D101: Per person | E101: ='Coaching Calculator'!D8 | F101: ='Coaching Calculator'!E8 | G101: ='Coaching Calculator'!F8 | H101: ='Coaching Calculator'!G8 | I101: ='Coaching Calculator'!H8 | J101: ='Coaching Calculator'!I8
B102: SPARK 2 | C102: ='Coaching Calculator'!B9 | D102: Per person | E102: ='Coaching Calculator'!D9 | F102: ='Coaching Calculator'!E9 | G102: ='Coaching Calculator'!F9 | H102: ='Coaching Calculator'!G9 | I102: ='Coaching Calculator'!H9 | J102: ='Coaching Calculator'!I9
B103: AIIR Vista (6 months) | C103: ='Coaching Calculator'!B10 | D103: Per person | E103: ='Coaching Calculator'!D10 | F103: ='Coaching Calculator'!E10 | G103: ='Coaching Calculator'!F10 | H103: ='Coaching Calculator'!G10 | I103: ='Coaching Calculator'!H10 | J103: ='Coaching Calculator'!I10
B104: AIIR Vista (12 months) | C104: ='Coaching Calculator'!B11 | D104: Per person | E104: ='Coaching Calculator'!D11 | F104: ='Coaching Calculator'!E11 | G104: ='Coaching Calculator'!F11 | H104: ='Coaching Calculator'!G11 | I104: ='Coaching Calculator'!H11 | J104: ='Coaching Calculator'!I11
...

Sheet Calculator
A1: Coaching Calculator
A2: Selected Tier:
A3: Coaching Cost Summary
A4: ITEM | B4: ITEM COST | C4: NOTE | D4: QUANTITY | E4: COST | F4: PM FEE | G4: COST W PM | H4: MARGIN | I4: CLIENT PRICE
A5: ROADMAP | B5: =if(ISNUMBER(D5),B32+H26," ") | C5: Per person | D5: =E31 | E5: =IF(ISNUMBER(D5), D5*B5, "") | F5: =IF(ISNUMBER(D5),D5*B31," ") | G5: =IF(ISNUMBER(D5), E5+F5, " ") | H5: =$B$16 | I5: =IF(AND(ISNUMBER(G5), H5<1), H32, "")
A6: IGNITE | B6: =IF(ISNUMBER(D6),B50+H42," ") | C6: Per person | D6: =E49 | E6: =IF(ISNUMBER(D6), D6*B6, "") | F6: =IF(ISNUMBER(D6),D6*B49," ") | G6: =IF(ISNUMBER(D6), E6+F6, " ") | H6: =$B$16 | I6: =IF(AND(ISNUMBER(G6), H6<1), H50, "")
A7: ASCENT | B7: =IF(ISNUMBER(D7),B68+H60," ") | C7: Per person | D7: =E67 | E7: =IF(ISNUMBER(D7), D7*B7, "") | F7: =IF(ISNUMBER(D7),D7*B67," ") | G7: =IF(ISNUMBER(D7), E7+F7, " ") | H7: =$B$16 | I7: =IF(AND(ISNUMBER(G7), H7<1), H68, "")
A8: SPARK 1 | B8: =IF(ISNUMBER(D8),B84+H78," ") | C8: Per person | D8: =E83 | E8: =IF(ISNUMBER(D8), D8*B8, "") | F8: =IF(ISNUMBER(D8),D8*B83," ") | G8: =IF(ISNUMBER(D8), E8+F8, " ") | H8: =$B$16 | I8: =IF(AND(ISNUMBER(G8), H8<1), H84, "")
A9: SPARK 2 | B9: =IF(ISNUMBER(D9),B102+H95," ") | C9: Per person | D9: =E101 | E9: =IF(ISNUMBER(D9), D9*B9, "") | F9: =IF(ISNUMBER(D9),D9*B101," ") | G9: =IF(ISNUMBER(D9), E9+F9, " ") | H9: =$B$16 | I9: =IF(AND(ISNUMBER(G9), H9<1), H102, "")
A10: AIIR Vista (6 months) | B10: =IF(ISNUMBER(D10),B120+H111," ") | C10: Per person | D10: =E119 | E10: =IF(ISNUMBER(D10), D10*B10, "") | F10: =IF(ISNUMBER(D10),D10*B119," ") | G10: =IF(ISNUMBER(D10), E10+F10, " ") | H10: =$B$16 | I10: =IF(AND(ISNUMBER(G10), H10<1), H120, "")
A11: AIIR Vista (12 months) | B11: =IF(ISNUMBER(D11),B138+H129," ") | C11: Per person | D11: =E137 | E11: =IF(ISNUMBER(D11), D11*B11, "") | F11: =IF(ISNUMBER(D11),D11*B137," ") | G11: =IF(ISNUMBER(D11), E11+F11, " ") | H11: =$B$16 | I11: =IF(AND(ISNUMBER(G11), H11<1), H138, "")
A12: EXECUTIVE COACHING TOTAL: | E12: =SUM(E3:E9) | F12: =SUM(F3:F9) | G12: =SUM(G3:G9) | I12: =SUM(I3:I9)
A14: Set Bill Rate and Margin for the Engagement | D14: Coach Hourly Rate Table | E14: Tier 1 | F14: Tier 2 | G14: C-Suite
A15: Coaching Bill Rate: | B15: 350 | D15: Mature Market | E15: 350 | F15: 250 | G15: 600
A16: Margin: | B16: 0.65 | D16: Emerging Market | E16: 300 | F16: 200 | G16: 500
A19: ROADMAP
A20: Sessions | B20: Coaching Hours | D20: Assessments & Fees | E20: # | F20: Rate | G20: Cost
A21: Initial Coaching Session | B21: 0.5 | D21: Coaching Zone Fee - months | E21: 6 | F21: 75 | G21: =E21*F21
A22: Stakeholder 1: Agenda Setting Meeting | B22: 1 | D22: LD12 360º | E22: 1 | F22: 350 | G22: =E22*F22
A23: Developmental History Interview | B23: 1.5 | D23: LD12 | F23: 150 | G23: =E23*F23
A24: Assessment Feedback Session | B24: 2 | D24: Hogan Insight | F24: 300 | G24: =E24*F24
A25: Development Planning Session | B25: 1 | D25: TES | F25: 500 | G25: =E25*F25
A26: Stakeholder 2: Presentation of SDP | B26: 1 | D26: Other: | G26: =E26*F26
A27: 5 Implementation Session | B27: 5 | D27: Other: | G27: =E27*F27
A28: Stakeholder 3: Wrap-Up Session | B28: 1 | G28: Total Assessments & Fees per Participant: | H28: =SUM(G21:G27)
A29: Total Hours per Participant: | B29: =sum(B21:B28) | G29: Total Services including margin: | H29: =B32/(1-$B$16)
A30: Total Coach Cost | B30: =B29*$B$15 | G30: Engagement Total Per Participant: | H30: =SUM(H26:H29)
A31: PM Fee (12%) | B31: =B30*0.12 | D31: # of Participants
A32: Total Services Cost (without margin): | B32: =SUM(B30:B31) | G32: Total for Engagement: | H32: =H30*E31
A35: IGNITE
A36: Sessions | B36: Coaching Hours | D36: Assessments & Fees | E36: # | F36: Rate | G36: Cost
A37: Initial Coaching Session | B37: 0.5 | C37: Default: 30 min | D37: Coaching Zone Fee - months | E37: 9 | F37: 75 | G37: =E37*F37
A38: Stakeholder 1: Agenda Setting Meeting | B38: 1 | C38: Default: 1 hr Min: 30 min | D38: LD12 360º | E38: 0 | F38: 350 | G38: =E38*F38
A39: Developmental History Interview | B39: 2 | C39: Default: 2 hrs Min: 90 min | D39: LD12 | E39: 1 | F39: 150 | G39: =E39*F39
A40: Interview-based 360º (up to 8 interviews) | B40: =(45*8)/60 | C40: Default: 8 mtgs * 45 min each = 6 hrs Min: 5 mtgs * 45 min each = 3.75 hrs | D40: Hogan Insight | E40: 1 | F40: 300 | G40: =E40*F40
A41: Assessment Feedback Session | B41: 2 | C41: Default: 2 hrs Min: 90 min | D41: TES | F41: 500 | G41: =E41*F41
A42: Development Planning Session | B42: 1 | C42: Default: 1 hr Min: 0 hrs | D42: Other: | G42: =E42*F42
A43: Stakeholder 2: Presentation of SDP | B43: 1 | C43: Default: 1 hr Min: 30 min | D43: Other: | G43: =E43*F43
A44: 8 Implementation Sessions | B44: 8 | C44: Default/Always: 8 sessions * 1 hr each | G44: Total Assessments & Fees per Participant: | H44: =SUM(G37:G43)
A45: Stakeholder 3: Mid-Point Check In | B45: 1 | C45: Default: 1 hr Min: 30 min
A46: Stakeholder 4: Wrap-Up Session | B46: 1 | C46: Default: 1 hr Min: 30 min
A47: Total Hours per Participant: | B47: =sum(B37:B46) | C47: Default: 23 - 23.5 hrs Min: 17.25 hrs | G47: Total Services including margin: | H47: =B50/(1-$B$16)
A48: Total Coach Cost | B48: =B47*$B$15 | G48: Engagement Total Per Participant: | H48: =SUM(H42:H47)
A49: PM Fee (12%) | B49: =B48*0.12 | D49: # of Participants
A50: Total Services Cost (without margin): | B50: =SUM(B48:B49) | G50: Total for Engagement: | H50: =H48*E49
A53: ASCENT
A54: Sessions | B54: Coaching Hours | D54: Assessments & Fees | E54: # | F54: Rate | G54: Cost
A55: Initial Coaching Session | B55: 0.5 | D55: Coaching Zone Fee - months | E55: 12 | F55: 50 | G55: =E55*F55
A56: Stakeholder 1: Agenda Setting Meeting | B56: 1 | D56: LD12 360º | E56: 1 | F56: 350 | G56: =E56*F56
A57: Developmental History Interview | B57: 2 | D57: LD12 | F57: 150 | G57: =E57*F57
A58: Interview-based 360º (up to 8 interviews) | B58: =(12*45)/60 | D58: Hogan Insight | F58: 300 | G58: =E58*F58
A59: Assessment Feedback Session | B59: 2 | D59: TES | F59: 500 | G59: =E59*F59
A60: Development Planning Session | B60: 1 | D60: Other: | G60: =E60*F60
A61: Stakeholder 2: Presentation of SDP | B61: 1 | D61: Other: | G61: =E61*F61
A62: 8 Implementation Sessions | B62: 12 | G62: Total Assessments & Fees per Participant: | H62: =SUM(G55:G61)
A63: Stakeholder 3: Mid-Point Check In | B63: 1
A64: Stakeholder 4: Wrap-Up Session | B64: 1
A65: Total Hours per Participant: | B65: =sum(B55:B64) | G65: Total Services including margin: | H65: =B68/(1-$B$16)
A66: Total Coach Cost | B66: =B65*$B$15 | G66: Engagement Total Per Participant: | H66: =SUM(H60:H65)
A67: PM Fee (12%) | B67: =B66*0.12 | D67: # of Participants
A68: Total Services Cost (without margin): | B68: =SUM(B66:B67) | G68: Total for Engagement: | H68: =H66*E67
A71: SPARK I
A72: Sessions | B72: Coaching Hours | D72: Assessments & Fees | E72: # | F72: Rate | G72: Cost
A73: Initial Coaching Session | B73: 0.5 | D73: Coaching Zone Fee - months | E73: 4 | F73: 75 | G73: =E73*F73
A74: Stakeholder 1: Agenda Setting Meeting | B74: 0.5 | D74: LD12 | E74: 1 | F74: 150 | G74: =E74*F74
A75: Assessment Feedback Session | B75: 1.5 | D75: Survey-based 360º | E75: 1 | F75: 350 | G75: =E75*F75
A76: Development Planning Session | B76: 1 | D76: Hogan Insight | E76: 1 | F76: 300 | G76: =E76*F76
A77: 3 Implementation Sessions | B77: 3 | D77: Developmental History Survey | E77: 1 | F77: 60 | G77: =E77*F77
A78: Stakeholder 2: Wrap-Up Session | B78: 0.5 | D78: Other: | G78: =E78*F78
A79: Total Hours per Participant: | B79: =sum(B73:B78) | D79: Other: | G79: =E79*F79
G80: Total Assessments & Fees per Participant: | H80: =SUM(G73:G79)
D81: Total Services including margin | H81: =B84/(1-$B$16)
A82: Total Coach Cost | B82: =B79*$B$15 | G82: Engagement Total Per Participant: | H82: =SUM(H76:H81)
A83: PM Fee (12%) | B83: =B82*0.12 | D83: # of Participants
A84: Total Services Cost (without margin): | B84: =SUM(B82:B83) | G84: Total for Engagement: | H84: =H82*E83
A89: SPARK II
A90: Sessions | B90: Coaching Hours | D90: Assessments & Fees | E90: # | F90: Rate | G90: Cost
A91: Initial Coaching Session | B91: 0.5 | D91: Coaching Zone Fee - months | E91: 5 | F91: 75 | G91: =E91*F91
A92: Stakeholder 1: Agenda Setting Meeting | B92: 0.5 | D92: LD12 | E92: 1 | F92: 350 | G92: =E92*F92
A93: Developmental History Interview | B93: 1 | D93: Survey-based 360º | F93: 150 | G93: =E93*F93
A94: Assessment Feedback Session | B94: 1.5 | D94: Hogan Insight | F94: 300 | G94: =E94*F94
A95: Development Planning Session | B95: 1 | D95: Other: | G95: =E95*F95
A96: Stakeholder 2: Presentation of SDP | B96: 0.5 | D96: Other: | G96: =E96*F96
A97: 5 Implementation Sessions | B97: 5 | G97: Total Assessments & Fees per Participant: | H97: =SUM(G90:G96)
A98: Stakeholder 3: Wrap-Up Session | B98: 0.5
A99: Total Hours per Participant: | B99: =sum(B91:B98) | G99: Total Services including margin: | H99: =B102/(1-$B$16)
A100: Total Coach Cost | B100: =B99*$B$15 | G100: Engagement Total Per Participant: | H100: =SUM(H94:H99)
A101: PM Fee (12%) | B101: =B100*0.12 | D101: # of Participants
A102: Total Services Cost (without margin): | B102: =SUM(B100:B101) | G102: Total for Engagement: | H102: =H100*E101
A105: AIIR VISTA: 6 MONTHS
A106: Sessions | B106: Coaching Hours | D106: Assessments & Fees | E106: # | F106: Rate | G106: Cost
A107: Kick-off Meeting | B107: 0.5 | D107: Coaching Zone Fee - months | E107: 6 | F107: 50 | G107: =E107*F107
A108: Stakeholder 1: Agenda Setting Meeting | B108: 1 | D108: LD12 | E108: 1 | F108: 350 | G108: =E108*F108
A109: Developmental History Interview | B109: 3 | D109: Hogan Insight | F109: 150 | G109: =E109*F109
A110: Interview-based 360º (up to 8 interviews) | B110: =(45*8)/60 | D110: TES | F110: 300 | G110: =E110*F110
A111: Assessment Feedback Session | B111: 2 | D111: Other: | G111: =E111*F111
A112: Development Planning Session | B112: 1 | D112: Other: | G112: =E112*F112
A113: Stakeholder 2: Presentation of SDP | B113: 1 | G113: Total Assessments & Fees per Participant: | H113: =SUM(G106:G112)
A114: Implementation Session | B114: 8
A115: Stakeholder 3: Mid-Point Check In | B115: 1
...

Sheet Deliverable Glossary
B1: DELIVERABLE | C1: DESCRIPTION
A2: Design | B2: Learning Design Sprint (Design Document) | C2: A focused, collaborative engagement that helps organizations move from strategy to a high-level program design and implementation plan – fast. Provides a structured process (design document) to clarify purpose, align on design principles, and map out a launch plan for each program.
B3: F2F Hackathon - 1 Day | C3: A collaborative, creative 1-day experience that brings together AIIR solutions architects and client partners to co-create learning deliverables.
B4: F2F Hackathon - 2 Day | C4: A collaborative, creative 2-day experience that brings together AIIR solutions architects and client partners to co-create learning deliverables.
B5: F2F Hackathon - 3 Day | C5: A collaborative, creative 3-day experience that brings together AIIR solutions architects and client partners to co-create learning deliverables.
B6: F2F Hackathon - 4 Day | C6: A collaborative, creative 4-day experience that brings together AIIR solutions architects and client partners to co-create learning deliverables.
B7: F2F Hackathon - 5 Day | C7: A collaborative, creative 5-day experience that brings together AIIR solutions architects and client partners to co-create learning deliverables.
B8: Virtual Hackathon - 4hr | C8: A collaborative, creative 1/2-day virtual experience that brings together AIIR solutions architects and client partners to co-create learning deliverables.
B9: Virtual Hackathon - 8hr | C9: A collaborative, creative 1-day virtual experience that brings together AIIR solutions architects and client partners to co-create learning deliverables.
B11: DELIVERABLE | C11: DESCRIPTION
A12: Development | B12: Pre-Program Capstone | C12: A session designed to introduce a capstone project/business challenges, divide participants into teams, and provide structured time to plan their project and assign accountabilities. Available F2F or Virtual.
B13: Post-Program Capstone | C13: A session designed to give participants a platform to present back their results and recommendations following the completion of their chosen capstone project. Available F2F or Virtual.
B14: Immersive Learning Offsite (F2F) | C14: Bespoke learning event design bringing together a unique combination of AIIR content, new models, immersive experiences, simulated scenarios, and keynote speakers.
B15: Learning Circle (Virtual) | C15: A structured, yet informal, group reinforcement experience designed to foster reflection, accountability, and peer-supported growth
B16: Immersive Virtual Engagement - Nudge | C16: Sustainment tool designed to reinforce behavior learned in an Immersive Learning Offsite, and provide participants with a challenge/case study for an upcoming Immersive Virtual Engagement Session.
B17: Immersive Virtual Engagement - Session | C17: Bespoke virtual learning session designed to drive application of learning around an organizational challenge or case study.
B18: Insight Cafe | C18: Engagement session designed to build belief in a change initiative/learning journey. Participants are divided into groups, discuss provocative questions related to the journey, and what it means for them. Available F2F or Virtual.
B19: Skill-Build Workshop (Standard) | C19: No changes to the content of one standard AIIR module. For clients who are satisfied with an AIIR module, right of the shelf, with no content design changes.
B20: Skill-Build Workshop (Tailored) | C20: Light content changes to one standard AIIR module. For clients who are satisfied with an AIIR module, but would like the messaging and look of the content to fit better with their culture.
B21: Skill-Build Workshop (Customized) | C21: Significant changes to one standard AIIR module OR the merging of multiple AIIR modules into a new fit-for-purpose session. For clients who are satisfied with an AIIR module, but would like to alter the exercises/experience to fit their needs OR clients who want to draw from multiple AIIR modules to create a fit-for-purpose experience.
B22: Skill-Build Workshop (Bespoke) | C22: Client can request brand new content or change content any way they wish. For clients who are interested in combining AIIR content, with non-AIIR content, or want a “from scratch” experience.
B23: Behavior Activation Toolkit | C23: Sustainment tool designed to help participants practice the behaviors they’ve learned back on the job. Interactive PDF (12-15 pages) with the following inclusions: * Program roadmap * Skill-building tips * 3x tools per behavior/skill * List of further resources (books, articles, TED talks)
B24: Dialogue Toolkit (Leader as Teacher) | C24: Sustainment tool designed to help participants facilitate discussions about the content with others who have attended a learning program. Includes: * 15-20 slide facilitation deck * Facilitation notes (in deck)
... B26: Peer Coaching | C26: Either digital (interactive PDF) or physical conversation guide to facilitate peer-to-peer reflection and relationships. Contains: * Overview of journey * Guidance on interactions and conversations * Journey specific conversation prompts * Areas for note keeping and reflections
B27: Action Learning
B28: Principles/Values Workshop (Standard) | C28: No changes to the content of one standard AIIR module. For clients who are satisfied with an AIIR module to represent one of their leadership principles/values right of the shelf, with no content design changes. (NOTE: requires a strong facilitator brief to ensure connection to desired leadership principle/value.
B29: Principles/Values Workshop (Tailored) | C29: Light content changes to one standard AIIR module. For clients who are satisfied with an AIIR module to represent one of their leadership principles/values, but would like the messaging and look of the content to fit better with their culture.
B30: Principles/Values Workshop (Customized) | C30: Significant changes to one standard AIIR module OR the merging of multiple AIIR modules into a new fit-for-purpose session. For clients who are satisfied with an AIIR module to represent one of their leadership principles/values, but would like to alter the exercises/experience to fit their needs OR clients who want to draw from multiple AIIR modules to create a fit-for-purpose experience.
B31: Principles/Values Workshop (Bespoke) | C31: Client can request brand new content or change content any way they wish. For clients who are interested in combining AIIR content, with non-AIIR content, or want a “from scratch” experience around one of their leadership principles/values.
B32: Group Coaching | C32: Sustainment session, led by an expert AIIR coach, designed to reinforce behavior by reviewing previous content and/or creating deeper, unstructured discussion around it. Available F2F or Virtual.
B33: Assessment Group Debrief | C33: 2 hour interactive session designed to help participants understand the structure and science behind the assessment they completed, the benefits of taking it, how to interpret their results, and first reactions on what this means for them. Available F2F or Virtual.
B34: SkillStream (1 path) | C34: Highly interactive custom sustainment eLearning designed for participants to take a “watch” then “practice” approach individually, OR in small groups.
B35: SkillStream (2 path) | C35: Highly interactive custom sustainment eLearning designed for participants to take a “watch” then “practice” approach individually, AND in small groups.
B36: Learning Lab | C36: Custom sustainment eLearning designed to present participants common scenarios for which to practice their skills. Participants complete 3-5 case studies/scenarios of varying levels of difficulty, and receive tips and tactics as they work their way through scenarios.
B38: DELIVERABLE | C38: DESCRIPTION
A39: Assessment | B39: CMI Assessment | C39: Individual CMI assessment with detailed description of CMI model, individualized scores and development suggestions, and action planning tool included.
B40: CMI 360 | C40: 360 CMI assessment with comparison of self vs. rater scores, detailed scaled data including item by item breakdown and rater agreement metric, open-ended feedback, and a variety of data displays for easy analysis.
B41: CMI Group Report | C41: CMI assessment that compares scores for an entire cohort of respondents, including group comparison of coaching style and average coaching strategy scores.
B42: LD12™ Assessment (Self Report) | C42: The LD12™ provides a comprehensive map of leadership skills, pinpointing leaders' signature strengths and development opportunities.
B43: LD12™ 360 Assessment | C43: The LD12™ 360 combines self-assessment on leadership skills with comprehensive insights from direct reports, peers, and managers to get an individual’s complete leadership picture.
B44: Core Values Navigator | C44: Identifies the values that shape a leader’s choices, helping align actions with role demands and organizational goals.
B45: Hogan Insights Series | C45: Evaluates personality, potential derailers, and core drivers to reveal how leaders work, lead, and respond under stress.
B46: Leadership Genome | C46: Quantitative and qualitative process for establishing an ecologically valid leadership model for your organization.
B47: Leadership Blueprint Package | C47: An executive assessment package designed to define what great leadership looks like at your organization. Provides a clear, values-aligned leadership framework that defines expectations, anchors to your culture, and supports talent strategy.
B48: Leadership Insights Package | C48: An executive assessment package designed to understand the strengths and gaps that exist for your leaders. Provides a deep understanding of leaders’ strengths and opportunities through individual and group assessment data.
B49: Leadership Pipeline Package | C49: An executive assessment package designed to identify leadership potential and succession readiness. Focuses on identifying internal talent with the potential to step into key leadership roles, and supports strategic succession planning by assessing readiness and highlighting gaps.
B51: DELIVERABLE | C51: DESCRIPTION
A52: Team Effectiveness | B52: TES Assessment | C52: The Team Effectiveness Survey assesses the current state of a team's culture and productivity.
B53: TE Stakeholder Interview | C53: A confidential interview that is conducted with key stakeholders around the team to get their views on how the team is functioning.
B54: TE Perspectives | C54: Solution designed to help the team have a greater awareness of its ability to perform and create value. Teams will Identify team strengths and development opportunities, gather insights into their team’s culture and productivity, and create a Team Charter to set up their team’s purpose and operating principles.
B55: TE Roadmap | C55: Solution designed to help the team foster new behaviors that drive results of clearly defined business priorities. Teams will move beyond assessment and chartering to tackle a set of goals or challenges, and engage in a variety of team sessions with an expert Team Coach to break old patterns and shape new behaviors.
B56: TE Ignite | C56: Solution designed to help the team take an actionable leadership role in navigating organizational change. Teams will take it to the "next level" with extended team coaching for sustained high performance, and engage in sessions and activities that elevate their team’s performance in navigating a key challenge, change, or transformation.
B57: Team Coaching Session | C57: A 90-minute session that builds on the team's work from the Insight Session or addresses pressing needs as they arise.
B58: Team Leader Meeting | C58: A 60-minute session with the coach to prepare for, debrief on, or discuss adjustments to the team journey.
B59: Individual Assessment Debrief | C59: A 60-minute session where team members are taken through a debrief of their individual psychometric assessment.
B60: TE Coaching Zone Access | C60: This per-person fee provides access to AIIR's proprietary Coaching Zone technology and a variety of tools that can be used to enhance the team experience.
B62: DELIVERABLE | C62: DESCRIPTION
A63: Executive Coaching | B63: Spark 1 | C63: Coaching by certified coaches typically with 3-5 years of experience. 3-4 month coaching engagement designed to increase self-awareness and jumpstart a development plan. Includes: * 7 hours of coaching * Kick-Off Session * Leadership Assessments * AIIR Dynamics 360º Survey * Developmental History Survey * Assessment Feedback Session * Development Planning Session * 3 Implementation Sessions * 2 Stakeholder Meetings * Continuing Action Plan * Access to AIIRON (AIIR's Ai digital coach) * Access to Coaching Zone
B64: Spark 2 | C64: Coaching by certified coaches typically with 3-5 years of experience. 4-5 month coaching engagement designed to increase self-awareness and jumpstart a development plan. Includes: * 10.5 hours of coaching * Kick-Off Session * Leadership Assessments * AIIR Dynamics 360º Survey * Developmental History Survey * Assessment Feedback Session * Development Planning Session * 5 Implementation Sessions * 3 Stakeholder Meetings * Continuing Action Plan * Access to AIIRON (AIIR's Ai digital coach) * Access to Coaching Zone
B65: Roadmap | C65: Coaching by senior executive coaches. 4-6 month coaching engagement designed to accelerate effectiveness and achieve sustained behavior change. Includes: * 13 hours of coaching * Kick-Off Session * Leadership Assessments * AIIR Dynamics 360º Survey * Developmental History Survey * Assessment Feedback Session * Development Planning Session * 5 Implementation Sessions * 3 Stakeholder Meetings * Continuing Action Plan * Access to AIIRON (AIIR's Ai digital coach) * Access to Coaching Zone
B66: Ignite | C66: Coaching by senior executive coaches. 6-9 month coaching engagement designed to accelerate effectiveness and achieve sustained behavior change. Includes: * 23 hours of coaching * Kick-Off Session * Leadership Assessments * Interview-based 360º * Developmental History Survey * Assessment Feedback Session * Development Planning Session * 8 Implementation Sessions * 4 Stakeholder Meetings * Continuing Action Plan * Access to AIIRON (AIIR's Ai digital coach) * Access to Coaching Zone
B67: Ascent | C67: Coaching by senior executive coaches. 10-12 month coaching engagement designed to accelerate effectiveness and achieve sustained behavior change. Includes: * 30.5 hours of coaching * Kick-Off Session * Leadership Assessments * Interview-based 360º+ * Developmental History Survey * Assessment Feedback Session * Development Planning Session * 12 Implementation Sessions * 4 Stakeholder Meetings * Continuing Action Plan * Access to AIIRON (AIIR's Ai digital coach) * Access to Coaching Zone
B68: Vista | C68: Coaching by a presitigious group of elite executive coaches/consultants. 6 OR 12 month trusted leadership advisory to support an executive's ability to confront and deal with complexity, ambiguity, and intensity of their role. Includes: * On demand, 24/7 coaching support * Exclusive AIIR Vista Welcome Kit * Stakeholder sessions, assessments, and 360º as needed

Sheet Tracker
A1: engagement_id | B1: created_at | C1: transcript_filename | D1: client_company | E1: coachee_name | F1: hubspot_deal_id | G1: coach_name | H1: tier | I1: bill_rate | J1: num_participants | K1: price_per_participant | L1: total_engagement_price | M1: payment_structure | N1: net_days | O1: pricing_approval_status | P1: pricing_approved_by | Q1: pricing_approved_at | R1: rationale_doc_url | S1: calculator_url | T1: sow_doc_url | U1: sow_approval_status | V1: sow_approved_by | W1: sow_approved_at | X1: client_email | Y1: sent_at | Z1: archive_folder_url | AA1: full_variables_json
